django_rocshelf/__init__.py
django_rocshelf/apps.py
django_rocshelf/backends.py
django_rocshelf/mixins.py
django_rocshelf/urls.py
django_rocshelf/views.py
rocshelf/__init__.py
rocshelf/__main__.py
rocshelf/caching/__init__.py
rocshelf/cli.py
rocshelf/compile/__init__.py
rocshelf/compile/controller.py
rocshelf/compile/meta.py
rocshelf/compile/params.py
rocshelf/compile/routes.py
rocshelf/compile/static.py
rocshelf/compile/tracebacks.py
rocshelf/compile/utils.py
rocshelf/components/__init__.py
rocshelf/components/files.py
rocshelf/components/localization.py
rocshelf/components/media.py
rocshelf/components/relations.py
rocshelf/components/routes.py
rocshelf/components/shelves.py
rocshelf/components/static.py
rocshelf/config.py
rocshelf/daemon/__init__.py
rocshelf/exception.py
rocshelf/frontend/__init__.py
rocshelf/frontend/analyze.py
rocshelf/frontend/chunks.py
rocshelf/frontend/preloader.py
rocshelf/frontend/readme.md
rocshelf/integration/__init__.py
rocshelf/integration/interfaces.py
rocshelf/integration/save.py
rocshelf/main.py
rocshelf/readme.md
rocshelf/source/config.json
rocshelf/source/defaults/page_complect.html
rocshelf/source/groups/material/rocshelf-group.json
rocshelf/source/groups/rocshelf-groups.json
rocshelf/source/groups/tools/blocks/info/html.html
rocshelf/source/groups/tools/rocshelf-group.json
rocshelf/source/groups/tools/tags/modals/html.html
rocshelf/source/layouts/block/html.html
rocshelf/source/layouts/block/script.js
rocshelf/source/layouts/block/shelf.yaml
rocshelf/source/layouts/block/style.scss
rocshelf/source/layouts/html_link_css.html
rocshelf/source/layouts/html_link_js.html
rocshelf/source/layouts/html_links_final_css.html
rocshelf/source/layouts/page/html.html
rocshelf/source/layouts/page/script.js
rocshelf/source/layouts/page/shelf.yaml
rocshelf/source/layouts/page/style.scss
rocshelf/source/layouts/tag/html.html
rocshelf/source/layouts/tag/script.js
rocshelf/source/layouts/tag/shelf.yaml
rocshelf/source/layouts/tag/style.scss
rocshelf-0.2.11.dist-info/LICENSE
rocshelf-0.2.11.dist-info/WHEEL
rocshelf-0.2.11.dist-info/METADATA
rocshelf-0.2.11.dist-info/RECORD
